canonicalwebteam/__init__.py
canonicalwebteam/discourse/__init__.py
canonicalwebteam/discourse/app.py
canonicalwebteam/discourse/exceptions.py
canonicalwebteam/discourse/models.py
canonicalwebteam/discourse/parsers/__init__.py
canonicalwebteam/discourse/parsers/base_parser.py
canonicalwebteam/discourse/parsers/category.py
canonicalwebteam/discourse/parsers/docs.py
canonicalwebteam/discourse/parsers/events.py
canonicalwebteam/discourse/parsers/tutorials.py
canonicalwebteam_discourse-7.1.1.dist-info/licenses/LICENSE
tests/__init__.py
tests/test_app.py
tests/test_engage_pages.py
tests/test_models.py
tests/test_parser.py
tests/fixtures/__init__.py
tests/fixtures/forum_mock.py
canonicalwebteam_discourse-7.1.1.dist-info/METADATA
canonicalwebteam_discourse-7.1.1.dist-info/WHEEL
canonicalwebteam_discourse-7.1.1.dist-info/top_level.txt
canonicalwebteam_discourse-7.1.1.dist-info/RECORD
